pandas_nhanes/VERSION
pandas_nhanes/__init__.py
pandas_nhanes/api.py
pandas_nhanes/nhanes_variables.csv
pandas_nhanes/scrape_variables.py
pandas_nhanes-0.1.8.dist-info/licenses/LICENSE
pandas_nhanes-0.1.8.dist-info/METADATA
pandas_nhanes-0.1.8.dist-info/WHEEL
pandas_nhanes-0.1.8.dist-info/top_level.txt
pandas_nhanes-0.1.8.dist-info/RECORD
